files_utils.py
gstorage_backup.py
gstorage_backup-0.9.7.dist-info/LICENSE.txt
gstorage_backup-0.9.7.dist-info/METADATA
gstorage_backup-0.9.7.dist-info/WHEEL
gstorage_backup-0.9.7.dist-info/entry_points.txt
gstorage_backup-0.9.7.dist-info/top_level.txt
gstorage_backup-0.9.7.dist-info/RECORD
