Metadata-Version: 2.1
Name: gstorage-backup
Version: 0.9.7
Home-page: https://bitbucket.org/offertech/gstorage_backup
Author: Rodrigo F. Sacht
Author-email: rodrigofsacht@gmail.com
License: MIT
Keywords: gcp storage backup
License-File: LICENSE.txt
Requires-Dist: wheel
Requires-Dist: google-cloud-storage
Requires-Dist: fire
Requires-Dist: python-dotenv
Requires-Dist: python-slugify
